BrowserBatteries/__init__.py
BrowserBatteries/py.typed
BrowserBatteries/bin/grpc_server
robotframework_browser_batteries-19.12.4.dist-info/licenses/LICENSE
robotframework_browser_batteries-19.12.4.dist-info/METADATA
robotframework_browser_batteries-19.12.4.dist-info/WHEEL
robotframework_browser_batteries-19.12.4.dist-info/top_level.txt
robotframework_browser_batteries-19.12.4.dist-info/RECORD
