Metadata-Version: 2.4
Name: robotframework-browser-batteries
Version: 19.12.4
Summary: Robot Framework Browser batteries package which contains all necessary NodeJS side components for using the Browser library.
Author: MarketSquare - Robot Framework community
Maintainer-email: Tatu Aalto <aalto.aalto@gmail.com>, Mikko Korpela <mikko.korpela@gmail.com>, Kerkko Pelttari <kerk.pelt@gmail.com>, René Rohner <rene@robotframework.org>
License-Expression: Apache-2.0
Project-URL: Homepage, https://robotframework-browser.org/
Project-URL: Documentation, https://marketsquare.github.io/robotframework-browser/Browser.html
Project-URL: Repository, https://github.com/MarketSquare/robotframework-browser
Project-URL: Issues, https://github.com/MarketSquare/robotframework-browser/issues
Project-URL: Changelog, https://github.com/MarketSquare/robotframework-browser/tree/main/docs/releasenotes
Keywords: robotframework,playwright,testing,automation,web,browser
Classifier: Development Status :: 5 - Production/Stable
Classifier: Operating System :: OS Independent
Classifier: Programming Language :: Python :: 3
Classifier: Topic :: Software Development :: Testing
Classifier: Framework :: Robot Framework
Classifier: Framework :: Robot Framework :: Library
Requires-Python: >=3.10
License-File: LICENSE
Requires-Dist: robotframework-browser==19.12.4
Dynamic: license-file
